transistordatabase/__init__.py
transistordatabase/checker_functions.py
transistordatabase/colors.py
transistordatabase/constants.py
transistordatabase/data_classes.py
transistordatabase/database_manager.py
transistordatabase/diode.py
transistordatabase/exceptions.py
transistordatabase/exporter.py
transistordatabase/generalplotsettings.py
transistordatabase/helper_functions.py
transistordatabase/mongodb_handling.py
transistordatabase/switch.py
transistordatabase/transistor.py
transistordatabase/data/housing_types.txt
transistordatabase/data/module_manufacturers.txt
transistordatabase/examples/first_example.py
transistordatabase/examples/tdb_example/CREE_C3M0016120K.json
transistordatabase/examples/tdb_example/CREE_C3M0060065J.json
transistordatabase/examples/tdb_example/CREE_C3M0065100J.json
transistordatabase/examples/tdb_example/CREE_C3M0120065J.json
transistordatabase/examples/tdb_example/CREE_C3M0120100J.json
transistordatabase/examples/tdb_example/CREE_CAB530M12BM3.json
transistordatabase/examples/tdb_example/CREE_WAB300M12BM3.json
transistordatabase/examples/tdb_example/Fuji_2MBI100XAA120-50.json
transistordatabase/examples/tdb_example/Fuji_2MBI200XAA065-50.json
transistordatabase/examples/tdb_example/Fuji_2MBI200XBE120-50.json
transistordatabase/examples/tdb_example/Fuji_2MBI300XBE065-50.json
transistordatabase/examples/tdb_example/Fuji_2MBI300XBE120-50.json
transistordatabase/examples/tdb_example/Fuji_2MBI400U2B-060.json
transistordatabase/examples/tdb_example/Fuji_2MBI400XBE065-50.json
transistordatabase/examples/tdb_example/Fuji_2MBI600XEE065-50.json
transistordatabase/examples/tdb_example/GaNSystems_GS66506T.json
transistordatabase/examples/tdb_example/Infineon_FF200R12KE3.json
transistordatabase/examples/tdb_example/Infineon_FF300R12KE3.json
transistordatabase/examples/tdb_example/Infineon_IPBE65R050CFD7A.json
transistordatabase/examples/tdb_example/Infineon_IPW65R090CFD7.json
transistordatabase/examples/tdb_example/Mitsubishi_CM200DY-24T.json
transistordatabase-0.5.1.dist-info/LICENSE
transistordatabase-0.5.1.dist-info/METADATA
transistordatabase-0.5.1.dist-info/WHEEL
transistordatabase-0.5.1.dist-info/top_level.txt
transistordatabase-0.5.1.dist-info/RECORD
