Metadata-Version: 2.1
Name: transistordatabase
Version: 0.5.1
Summary: Transistor Database
Home-page: https://github.com/upb-lea/transistordatabase
Author: LEA - Uni Paderborn
Author-email: tdb@lea.upb.de
License: GNU General Public License v3
Project-URL: Documentation, https://upb-lea.github.io/transistordatabase/main/transistordatabase.html
Project-URL: Source Code, https://github.com/upb-lea/transistordatabase
Keywords: Transistordatabase
Classifier: Development Status :: 3 - Alpha
Classifier: Intended Audience :: Developers
Classifier: License :: OSI Approved :: GNU General Public License v3 (GPLv3)
Classifier: Natural Language :: English
Classifier: Topic :: Scientific/Engineering
Classifier: Programming Language :: Python :: 3
Classifier: Programming Language :: Python :: 3.8
Classifier: Programming Language :: Python :: 3.9
Classifier: Programming Language :: Python :: 3.10
Classifier: Operating System :: Microsoft :: Windows
Classifier: Operating System :: POSIX :: Linux
Classifier: Environment :: MacOS X
Requires-Python: >=3.8
License-File: LICENSE
Requires-Dist: numpy >=1.19.5
Requires-Dist: persistent >=4.6.4
Requires-Dist: scipy >=1.6.0
Requires-Dist: setuptools >=49.2.1
Requires-Dist: pymongo >=3.11.3
Requires-Dist: matplotlib >=3.3.4
Requires-Dist: Jinja2 >=3.0.1
Requires-Dist: packaging >=20.9
Requires-Dist: Pillow >=8.3.1
Requires-Dist: pytest >=6.2.4
Requires-Dist: PyQt5
Requires-Dist: PyQtWebEngine
Requires-Dist: mongomock
Requires-Dist: requests
Requires-Dist: deepdiff
